imbalance_xgboost-0.8.1.data/scripts/focal_loss.py
imbalance_xgboost-0.8.1.data/scripts/imbalance_xgb.py
imbalance_xgboost-0.8.1.data/scripts/weighted_loss.py
imxgboost/__init__.py
imxgboost/focal_loss.py
imxgboost/imbalance_xgb.py
imxgboost/weighted_loss.py
imbalance_xgboost-0.8.1.dist-info/LICENSE
imbalance_xgboost-0.8.1.dist-info/METADATA
imbalance_xgboost-0.8.1.dist-info/WHEEL
imbalance_xgboost-0.8.1.dist-info/top_level.txt
imbalance_xgboost-0.8.1.dist-info/RECORD
