Metadata-Version: 2.1
Name: imbalance-xgboost
Version: 0.8.1
Summary: XGBoost for label-imbalanced data: XGBoost with weighted and focal loss functions
Home-page: https://github.com/jhwjhw0123/Imbalance-XGBoost
Author: Chen Wang
Author-email: chen.wang.cs@rutgers.edu
License: MIT
Download-URL: https://github.com/jhwjhw0123/Imbalance-XGBoost
Platform: UNKNOWN
Classifier: Programming Language :: Python :: 3
Classifier: Programming Language :: Python :: 3.5
Classifier: Programming Language :: Python :: 3.6
Classifier: License :: OSI Approved :: MIT License
Classifier: Operating System :: OS Independent
Classifier: Intended Audience :: Science/Research
Requires-Dist: numpy (>=1.11)
Requires-Dist: scikit-learn (>=0.19)
Requires-Dist: xgboost (>=1.1.1)
